demos/SWAP.py
demos/__init__.py
demos/quito_test.py
quito/__init__.py
quito/quito_coverage.py
quito-1.1.1.dist-info/LICENSE.py
quito-1.1.1.dist-info/METADATA
quito-1.1.1.dist-info/WHEEL
quito-1.1.1.dist-info/entry_points.txt
quito-1.1.1.dist-info/top_level.txt
quito-1.1.1.dist-info/RECORD
