Metadata-Version: 2.1
Name: quito
Version: 1.1.1
Summary: A coverage guided test generator for quantum programs
Home-page: https://github.com/Simula-COMPLEX/quito
Author: Xinyi Wang
Author-email: xinyi@simula.no
Classifier: Programming Language :: Python :: 3
Classifier: License :: OSI Approved :: MIT License
Classifier: Operating System :: OS Independent
Requires-Python: >=3.8
License-File: LICENSE.py
Requires-Dist: qiskit ==1.2.1
Requires-Dist: qiskit-aer ==0.15.1
